async_iterator/__init__.py
async_iterator/core.py
async_iterator-0.1.1.dist-info/LICENSE
async_iterator-0.1.1.dist-info/METADATA
async_iterator-0.1.1.dist-info/WHEEL
async_iterator-0.1.1.dist-info/RECORD
